{"cameraMode":{"drawMode":0,"name":"Shaded","section":"Shading Mode"},"sceneLighting":true,"audioPlay":false,"sceneViewState":{"showFog":true,"showMaterialUpdate":false,"showSkybox":true,"showFlares":true,"showImageEffects":true,"showParticleSystems":true},"in2DMode":false,"pivot":{"x":547.9853515625,"y":168.69471740722657,"z":-112.34478759765625},"rotation":{"x":0.10197587311267853,"y":-0.3940371870994568,"z":0.04404241219162941,"w":0.9123615026473999},"size":10.556417465209961,"orthographic":false}