{"cameraMode":{"drawMode":0,"name":"Shaded","section":"Shading Mode"},"sceneLighting":true,"audioPlay":false,"sceneViewState":{"showFog":true,"showMaterialUpdate":false,"showSkybox":true,"showFlares":true,"showImageEffects":true,"showParticleSystems":true},"in2DMode":false,"pivot":{"x":563.1286010742188,"y":166.89671325683595,"z":-127.0089111328125},"rotation":{"x":0.0016827555373311043,"y":-0.9763463735580444,"z":0.21608582139015199,"w":0.007607515435665846},"size":9.119185447692871,"orthographic":false}